hypertrack/__init__.py
hypertrack/devices.py
hypertrack/exceptions.py
hypertrack/geofences.py
hypertrack/ht_session.py
hypertrack/rest.py
hypertrack/trips.py
hypertrack/tests/__init__.py
hypertrack/tests/tests.py
hypertrack-3.0.5.dist-info/LICENSE
hypertrack-3.0.5.dist-info/METADATA
hypertrack-3.0.5.dist-info/WHEEL
hypertrack-3.0.5.dist-info/top_level.txt
hypertrack-3.0.5.dist-info/RECORD
