Metadata-Version: 2.1
Name: hypertrack
Version: 3.0.5
Summary: HyperTrack API wrapper
Home-page: https://www.hypertrack.com/
Author: HyperTrack
Author-email: help@hypertrack.com
Classifier: Programming Language :: Python :: 3
Classifier: License :: OSI Approved :: MIT License
Classifier: Operating System :: OS Independent
Requires-Python: >=3.6
License-File: LICENSE
Requires-Dist: requests >=2.31.0
